bgameb/__init__.py
bgameb/_version.py
bgameb/base.py
bgameb/errors.py
bgameb/game.py
bgameb/items.py
bgameb/players.py
bgameb/tools.py
bgameb-2.0.0.dist-info/LICENSE
bgameb-2.0.0.dist-info/METADATA
bgameb-2.0.0.dist-info/WHEEL
bgameb-2.0.0.dist-info/top_level.txt
bgameb-2.0.0.dist-info/RECORD
